tge/__init__.py
tge/animation.py
tge/camera.py
tge/debug.py
tge/display.py
tge/engine.py
tge/lights.py
tge/model.py
tge/util.py
tge-0.1.0.dist-info/METADATA
tge-0.1.0.dist-info/WHEEL
tge-0.1.0.dist-info/RECORD
