Metadata-Version: 2.1
Name: tge
Version: 0.1.0
Summary: 
Author: Jayden Edara
Author-email: aedara@uw.edu
Requires-Python: >=3.10,<3.13
Classifier: Programming Language :: Python :: 3
Classifier: Programming Language :: Python :: 3.10
Classifier: Programming Language :: Python :: 3.11
Classifier: Programming Language :: Python :: 3.12
Requires-Dist: matplotlib (>=3.8.2,<4.0.0)
Requires-Dist: numpy (>=1.26.1,<2.0.0)
